[
  {
    "tags": ["Essential"],
    "title": "Introduction to Information Design and Visualization",
    "authors": [
      {
        "name": "Alberto Cairo"
      }
    ]
  },
  {
    "tags": ["Conceptual"],
    "title": "The Craft of Building Stories with Data",
    "authors": [
      {
        "name": "Gurman Bhatia"
      }
    ]
  },
  {
    "tags": ["Conceptual"],
    "title": "Applied Data Ethics",
    "authors": [
      {
        "name": "Bridget Winds Cogley"
      }
    ]
  },
  {
    "tags": ["Conceptual"],
    "title": "How to Read Charts",
    "authors": [
      {
        "name": "Enrico Bertini"
      }
    ]
  },
  {
    "tags": ["Conceptual"],
    "title": "Feminist Data Visualization",
    "authors": [
      {
        "name": "Lauren Klein"
      },
      {
        "name": "Catherine D'Ignazio"
      }
    ]
  },
  {
    "tags": ["Conceptual"],
    "title": "History of Visualization",
    "authors": [
      {
        "name": "Michael Friendly"
      }
    ]
  },
  {
    "tags": ["Conceptual"],
    "title": "Accessibility in Visualization",
    "authors": [
      {
        "name": "Frank Elavsky"
      }
    ]
  },
  {
    "tags": ["Conceptual"],
    "title": "Generative AI for Data Analysis Visualization",
    "authors": [
      {
        "name": "Joy Victor"
      }
    ]
  },
  {
    "tags": ["Technical"],
    "title": "Adobe Illustrator for Infographics and Visualization",
    "authors": [
      {
        "name": "Hiram Henriquez"
      }
    ]
  },
  {
    "tags": ["Technical"],
    "title": "R for Data Preparation, Exploration, and Visualization",
    "authors": [
      {
        "name": "Raymond Balise"
      }
    ]
  },
  {
    "tags": ["Technical"],
    "title": "Python for Visualization",
    "authors": [
      {
        "name": "James McKenney"
      }
    ]
  },
  {
    "tags": ["Technical"],
    "title": "Visualization with Flourish",
    "authors": [
      {
        "name": "Alberto Cairo"
      }
    ]
  },
  {
    "tags": ["Technical"],
    "title": "Visualization with Datawrapper",
    "authors": [
      {
        "name": "Luís Melgar"
      }
    ]
  },
  {
    "tags": ["Technical"],
    "title": "RawGraphs for Visualization",
    "authors": [
      {
        "name": "Hannah Dormido"
      }
    ]
  },
  {
    "tags": ["Technical"],
    "title": "Figma for Visualization",
    "authors": [
      {
        "name": "Rodolfo Almeida"
      }
    ]
  },
  {
    "tags": ["Conceptual", "Technical"],
    "title": "Cartography and Map Design with QGIS",
    "authors": [
      {
        "name": "Hannah Dormido"
      }
    ]
  },
  {
    "tags": ["Conceptual", "Technical"],
    "title": "Designing Dashboards",
    "authors": [
      {
        "name": "Bridget Winds Cogley"
      }
    ]
  },
  {
    "tags": ["Personal"],
    "title": "Shirley Wu’s Design Philosophy",
    "authors": [
      {
        "name": "Shirley Wu"
      }
    ]
  },
  {
    "tags": ["Personal"],
    "title": "Sonja Kuijper’s Design Philosophy",
    "authors": [
      {
        "name": "Sonja Kuijper"
      }
    ]
  },
  {
    "tags": ["Personal"],
    "title": "Deniz Cem Önduygu’s Design Philosophy",
    "authors": [
      {
        "name": "Deniz Cem Önduygu"
      }
    ]
  },
  {
    "tags": ["Personal"],
    "title": "Visualization as a Craft",
    "authors": [
      {
        "name": "RJ Andrews"
      },
      {
        "name": "Alberto Cairo"
      },
      {
        "name": "Nadieh Bremer"
      }
    ]
  }
]
